Metadata-Version: 1.1
Name: djmodal
Version: 0.0.2
Summary: Django run app
Home-page: https://github.com/pmaigutyak/djmodal
Author: Paul Maigutyak
Author-email: pmaigutyak@gmail.com
License: MIT
Download-URL: https://github.com/pmaigutyak/djmodal/archive/0.0.2.tar.gz
Platform: UNKNOWN
